mcp_jina_reader/__init__.py
mcp_jina_reader/__main__.py
mcp_jina_reader/server.py
mcp_jina_reader-1.0.6.dist-info/METADATA
mcp_jina_reader-1.0.6.dist-info/WHEEL
mcp_jina_reader-1.0.6.dist-info/entry_points.txt
mcp_jina_reader-1.0.6.dist-info/RECORD
