Metadata-Version: 2.4
Name: mcp-jina-reader
Version: 1.0.6
Summary: url reader powered by jina ai reader
Author-email: fish <lechuanyu@foxmail.com>
Requires-Python: >=3.10
Requires-Dist: httpx>=0.28.1
Requires-Dist: mcp[cli]>=1.6.0
Requires-Dist: requests>=2.32.3
